restalchemy/__init__.py
restalchemy/version.py
restalchemy/api/__init__.py
restalchemy/api/actions.py
restalchemy/api/applications.py
restalchemy/api/constants.py
restalchemy/api/contexts.py
restalchemy/api/controllers.py
restalchemy/api/field_permissions.py
restalchemy/api/packers.py
restalchemy/api/resources.py
restalchemy/api/routes.py
restalchemy/api/middlewares/__init__.py
restalchemy/api/middlewares/contexts.py
restalchemy/api/middlewares/errors.py
restalchemy/api/middlewares/logging.py
restalchemy/api/middlewares/logging_http.py
restalchemy/api/middlewares/metrics.py
restalchemy/api/middlewares/retry_on_error.py
restalchemy/cmd/__init__.py
restalchemy/cmd/apply_migration.py
restalchemy/cmd/new_migration.py
restalchemy/cmd/rename_migrations.py
restalchemy/cmd/rollback_migration.py
restalchemy/common/__init__.py
restalchemy/common/config.py
restalchemy/common/config_opts.py
restalchemy/common/constants.py
restalchemy/common/contexts.py
restalchemy/common/exceptions.py
restalchemy/common/log.py
restalchemy/common/singletons.py
restalchemy/common/status.py
restalchemy/common/utils.py
restalchemy/dm/__init__.py
restalchemy/dm/filters.py
restalchemy/dm/models.py
restalchemy/dm/properties.py
restalchemy/dm/relationships.py
restalchemy/dm/types.py
restalchemy/dm/types_dynamic.py
restalchemy/dm/types_network.py
restalchemy/openapi/__init__.py
restalchemy/openapi/constants.py
restalchemy/openapi/engines.py
restalchemy/openapi/impl303.py
restalchemy/openapi/parse.py
restalchemy/openapi/structures.py
restalchemy/openapi/utils.py
restalchemy/storage/__init__.py
restalchemy/storage/base.py
restalchemy/storage/exceptions.py
restalchemy/storage/sql/__init__.py
restalchemy/storage/sql/constants.py
restalchemy/storage/sql/engines.py
restalchemy/storage/sql/filters.py
restalchemy/storage/sql/migration_templ.tmpl
restalchemy/storage/sql/migrations.py
restalchemy/storage/sql/orm.py
restalchemy/storage/sql/sessions.py
restalchemy/storage/sql/tables.py
restalchemy-15.0.1.dist-info/licenses/AUTHORS
restalchemy-15.0.1.dist-info/licenses/LICENSE
restalchemy-15.0.1.dist-info/METADATA
restalchemy-15.0.1.dist-info/WHEEL
restalchemy-15.0.1.dist-info/entry_points.txt
restalchemy-15.0.1.dist-info/pbr.json
restalchemy-15.0.1.dist-info/top_level.txt
restalchemy-15.0.1.dist-info/RECORD
