Metadata-Version: 2.4
Name: restalchemy
Version: 15.0.1
Summary: REST HTTP Abstraction Library
Home-page: https://github.com/infraguys/restalchemy
Author: Eugene Frolov
Author-email: eugene@frolov.net.ru
Classifier: Intended Audience :: Developers
Classifier: License :: OSI Approved :: Apache Software License
Classifier: Operating System :: POSIX :: Linux
Classifier: Programming Language :: Python
Classifier: Programming Language :: Python :: 3.8
Classifier: Programming Language :: Python :: 3.10
Classifier: Programming Language :: Python :: 3.12
Classifier: Programming Language :: Python :: 3.13
License-File: LICENSE
License-File: AUTHORS
Requires-Dist: pbr<=5.8.1,>=1.10.0
Requires-Dist: WebOb<1.9.0,>=1.8.9
Requires-Dist: requests<3.0.0,>=2.32.4
Requires-Dist: mysql-connector-python==8.4.0
Requires-Dist: oslo.config<8,>=3.22.0
Requires-Dist: PyYAML>=6.0
Requires-Dist: netaddr>=0.7.18
Requires-Dist: psycopg[binary,pool]<4.0.0,>=3.2.4
Requires-Dist: email-validator<3.0.0,>=2.2.0
Requires-Dist: orjson<4.0.0,>=3.10.0
Dynamic: author
Dynamic: author-email
Dynamic: classifier
Dynamic: description
Dynamic: home-page
Dynamic: license-file
Dynamic: requires-dist
Dynamic: summary
